btaps
