Metadata-Version: 1.1
Name: plugable-btaps
Version: 0.8.3
Summary: Open Source Library for Controlling the Plugable PS-BTAPS1 Bluetooth AC Outlet Switch
Home-page: https://github.com/bernieplug/plugable-btaps
Author: Plugable Technologies
Author-email: ivan@plugable.com
License: MIT
Keywords: bluetooth home-automation
Platform: UNKNOWN
Classifier: Development Status :: 3 - Alpha
Classifier: Intended Audience :: Developers
Classifier: Topic :: Home Automation
Classifier: License :: OSI Approved :: MIT License
Classifier: Programming Language :: Python :: 2 :: Only
Classifier: Programming Language :: Python :: 2.7
Classifier: Environment :: Console
Classifier: Operating System :: Microsoft :: Windows
Classifier: Operating System :: POSIX :: Linux
